login/__init__.py
login/login.py
wwidget_pkg/__init__.py
wwidget-0.0.7.dist-info/LICENSE.txt
wwidget-0.0.7.dist-info/METADATA
wwidget-0.0.7.dist-info/WHEEL
wwidget-0.0.7.dist-info/top_level.txt
wwidget-0.0.7.dist-info/RECORD
