Metadata-Version: 2.1
Name: wwidget
Version: 0.0.7
Summary: A package to fast embed HTML snippets to any websites or applications
Home-page: https://github.com/chheunpheara/wwidget
Author: Phearaeun
Author-email: siphearaeun@gmail.com
License: UNKNOWN
Platform: UNKNOWN
Classifier: Programming Language :: Python :: 3
Classifier: License :: OSI Approved :: MIT License
Classifier: Operating System :: OS Independent
Requires-Python: >=3.6
